tests/PexpectTestCase.py
tests/__init__.py
tests/echo_w_prompt.py
tests/exit1.py
tests/foo.py
tests/lines_printer.py
tests/list100.py
tests/long_printer.py
tests/needs_kill.py
tests/parametric_printer.py
tests/pyinstaller_test.py
tests/test_command_list_split.py
tests/test_console_reader.py
tests/test_constructor.py
tests/test_delay.py
tests/test_destructor.py
tests/test_echo.py
tests/test_expect.py
tests/test_interact.py
tests/test_isalive.py
tests/test_long.py
tests/test_misc.py
tests/test_misc_console_coverage.py
tests/test_parametric_printer.py
tests/test_parametric_printer_coverage.py
tests/test_readline.py
tests/test_run.py
tests/test_timeout_pattern.py
tests/utils.py
wexpect_venv/__init__.py
wexpect_venv/__main__.py
wexpect_venv/console_reader.py
wexpect_venv/host.py
wexpect_venv/legacy_wexpect.py
wexpect_venv/wexpect_util.py
wexpect_venv-4.0.3.dist-info/LICENSE
wexpect_venv-4.0.3.dist-info/METADATA
wexpect_venv-4.0.3.dist-info/WHEEL
wexpect_venv-4.0.3.dist-info/top_level.txt
wexpect_venv-4.0.3.dist-info/RECORD
