Metadata-Version: 2.1
Name: wexpect-venv
Version: 4.0.3
Summary: Fork of WExpect, a Windows alternative of pexpect
Home-page: UNKNOWN
Author: Noah Spurrier, Richard Holden, Marco Molteni, Kimberley Burchett, Robert Stone, Hartmut Goebel, Chad Schroeder, Erick Tryzelaar, Dave Kirby, Ids vander Molen, George Todd, Noel Taylor, Nicolas D. Cesar, Alexander Gattin, Geoffrey Marshall, Francisco Lourenco, Glen Mabey, Karthik Gurusamy, Fernando Perez, Corey Minyard, Jon Cohen, Guillaume Chazarain, Andrew Ryan, Nick Craig-Wood, Andrew Stone, Jorgen Grahn, Benedek Racz
Author-email: info@clear.ml
License: MIT
Project-URL: Source Code, https://github.com/allegroai/wexpect-venv
Keywords: scripting, automation, expect, pexpect, wexpect
Platform: UNKNOWN
Classifier: Development Status :: 4 - Beta
Classifier: Environment :: Console
Classifier: Intended Audience :: Developers
Classifier: Intended Audience :: Information Technology
Classifier: Operating System :: Microsoft :: Windows
Classifier: Programming Language :: Python :: 3.3
Classifier: Programming Language :: Python :: 3.4
Classifier: Programming Language :: Python :: 3.5
Classifier: Programming Language :: Python :: 3.6
Classifier: Programming Language :: Python :: 3.7
Classifier: Programming Language :: Python :: 3.8
Classifier: Programming Language :: Python :: 3.9
Classifier: Programming Language :: Python :: 3.10
Classifier: Programming Language :: Python :: 3.11
Classifier: Programming Language :: Python :: 3.12
Provides-Extra: test
Requires-Dist: coverage ; extra == 'test'
Requires-Dist: tox ; extra == 'test'
Requires-Dist: setuptools (>=38.0) ; extra == 'test'
Requires-Dist: codecov ; extra == 'test'
Requires-Dist: twine ; extra == 'test'
Requires-Dist: pyinstaller ; extra == 'test'
